<?xml version="1.0" encoding="utf-8"?>
<!-- Be careful where comments are placed! -->
<Values>
  <Boolean>
    <Setting>
      <PropertyName/>
      <PropertyValue>false</PropertyValue>
    </Setting>
  </Boolean>

  <Integer>
    <Setting>
      <PropertyName>StartingYear</PropertyName>
      <PropertyValue>2700</PropertyValue>
    </Setting>
    <Setting>
      <PropertyName>DaysPerYear</PropertyName>
      <PropertyValue>100</PropertyValue>
    </Setting>
  </Integer>

  <Float>
    <Setting>
      <PropertyName>DaysPerSecond</PropertyName>
      <PropertyValue>0.1</PropertyValue>
    </Setting>
    <Setting>
      <PropertyName>InjuredHealthThreshold</PropertyName>
      <PropertyValue>0.80</PropertyValue>
    </Setting>
    <Setting>
      <PropertyName>CriticalHealthThreshold</PropertyName>
      <PropertyValue>0.40</PropertyValue>
    </Setting>
  </Float>
</Values>
<!-- Elements are only empty if they are in the format <ElementName/> -->
