<?xml version="1.0" encoding="utf-8"?>
<!-- Be careful where comments are placed! -->

<!-- Client is SpeciesStatXmlReader : AXmlReader -->

<Values>
  <Species SpeciesName="Human">
      <PluralName>Humans</PluralName>
      <Description>Human Description...</Description>
      <ImageAtlasID>MyGui</ImageAtlasID>
      <ImageFilename>image</ImageFilename>
      <SensorRangeMultiplier>1.0</SensorRangeMultiplier>
      <WeaponRangeMultiplier>1.0</WeaponRangeMultiplier>
      <ActiveCountermeasureRangeMultiplier>1.0</ActiveCountermeasureRangeMultiplier>
      <WeaponReloadPeriodMultiplier>1.0</WeaponReloadPeriodMultiplier>
      <ActiveCountermeasureReloadPeriodMultiplier>1.0</ActiveCountermeasureReloadPeriodMultiplier>
  </Species>
  <Species SpeciesName="Klingon">
    <PluralName>Klingons</PluralName>
    <Description>Klingon Description...</Description>
    <ImageAtlasID>MyGui</ImageAtlasID>
    <ImageFilename>image</ImageFilename>
    <SensorRangeMultiplier>1.0</SensorRangeMultiplier>
    <WeaponRangeMultiplier>0.9</WeaponRangeMultiplier>
    <ActiveCountermeasureRangeMultiplier>1.0</ActiveCountermeasureRangeMultiplier>
    <WeaponReloadPeriodMultiplier>1.0</WeaponReloadPeriodMultiplier>
    <ActiveCountermeasureReloadPeriodMultiplier>1.0</ActiveCountermeasureReloadPeriodMultiplier>
  </Species>
  <Species SpeciesName="Ferengi">
    <PluralName>Ferengii</PluralName>
    <Description>Ferengi Description...</Description>
    <ImageAtlasID>MyGui</ImageAtlasID>
    <ImageFilename>image</ImageFilename>
    <SensorRangeMultiplier>1.0</SensorRangeMultiplier>
    <WeaponRangeMultiplier>1.1</WeaponRangeMultiplier>
    <ActiveCountermeasureRangeMultiplier>1.0</ActiveCountermeasureRangeMultiplier>
    <WeaponReloadPeriodMultiplier>1.0</WeaponReloadPeriodMultiplier>
    <ActiveCountermeasureReloadPeriodMultiplier>1.0</ActiveCountermeasureReloadPeriodMultiplier>
  </Species>
  <Species SpeciesName="Romulan">
    <PluralName>Romulans</PluralName>
    <Description>Romulan Description...</Description>
    <ImageAtlasID>MyGui</ImageAtlasID>
    <ImageFilename>image</ImageFilename>
    <SensorRangeMultiplier>1.0</SensorRangeMultiplier>
    <WeaponRangeMultiplier>1.05</WeaponRangeMultiplier>
    <ActiveCountermeasureRangeMultiplier>1.0</ActiveCountermeasureRangeMultiplier>
    <WeaponReloadPeriodMultiplier>1.0</WeaponReloadPeriodMultiplier>
    <ActiveCountermeasureReloadPeriodMultiplier>1.0</ActiveCountermeasureReloadPeriodMultiplier>
  </Species>
  <Species SpeciesName="Borg">
    <PluralName>Borg</PluralName>
    <Description>Borg Description...</Description>
    <ImageAtlasID>MyGui</ImageAtlasID>
    <ImageFilename>image</ImageFilename>
    <SensorRangeMultiplier>1.0</SensorRangeMultiplier>
    <WeaponRangeMultiplier>1.15</WeaponRangeMultiplier>
    <ActiveCountermeasureRangeMultiplier>1.0</ActiveCountermeasureRangeMultiplier>
    <WeaponReloadPeriodMultiplier>1.0</WeaponReloadPeriodMultiplier>
    <ActiveCountermeasureReloadPeriodMultiplier>1.0</ActiveCountermeasureReloadPeriodMultiplier>
  </Species>
  <Species SpeciesName="Dominion">
    <PluralName>Dominions</PluralName>
    <Description>Dominion Description...</Description>
    <ImageAtlasID>MyGui</ImageAtlasID>
    <ImageFilename>image</ImageFilename>
    <SensorRangeMultiplier>1.0</SensorRangeMultiplier>
    <WeaponRangeMultiplier>0.95</WeaponRangeMultiplier>
    <ActiveCountermeasureRangeMultiplier>1.0</ActiveCountermeasureRangeMultiplier>
    <WeaponReloadPeriodMultiplier>1.0</WeaponReloadPeriodMultiplier>
    <ActiveCountermeasureReloadPeriodMultiplier>1.0</ActiveCountermeasureReloadPeriodMultiplier>
  </Species>
  <Species SpeciesName="GodLike">
    <PluralName>GodLikes</PluralName>
    <Description>GodLike Description...</Description>
    <ImageAtlasID>MyGui</ImageAtlasID>
    <ImageFilename>image</ImageFilename>
    <SensorRangeMultiplier>1.0</SensorRangeMultiplier>
    <WeaponRangeMultiplier>1.2</WeaponRangeMultiplier>
    <ActiveCountermeasureRangeMultiplier>1.0</ActiveCountermeasureRangeMultiplier>
    <WeaponReloadPeriodMultiplier>1.0</WeaponReloadPeriodMultiplier>
    <ActiveCountermeasureReloadPeriodMultiplier>1.0</ActiveCountermeasureReloadPeriodMultiplier>
  </Species>
</Values>